setup.py
slacksender/__init__.py
ssend.egg-info/PKG-INFO
ssend.egg-info/SOURCES.txt
ssend.egg-info/dependency_links.txt
ssend.egg-info/entry_points.txt
ssend.egg-info/requires.txt
ssend.egg-info/top_level.txt