Metadata-Version: 1.1
Name: ssend
Version: 0.1.3
Summary: Send messages to a room/user in slack from the command line
Home-page: https://github.com/sarlalian/ssend
Author: Will L. Fife
Author-email: sarlalian+pip@gmail.com
License: MIT
Platform: UNKNOWN
Classifier: Programming Language :: Python
Classifier: Programming Language :: Python :: 2.7
Classifier: Programming Language :: Python :: 3.3
Classifier: Programming Language :: Python :: 3.4
Classifier: Programming Language :: Python :: 3.5
